argsclass/__init__.py
argsclass/ambiguity.py
argsclass/argparse_parser.py
argsclass/config.py
argsclass/descriptors.py
argsclass/exceptions.py
argsclass/help.py
argsclass/inspector.py
argsclass/parser.py
argsclass/models/__init__.py
argsclass/models/argspec.py
argsclass/models/types.py
argsclass-0.4.1.dist-info/licenses/LICENSE
argsclass-0.4.1.dist-info/METADATA
argsclass-0.4.1.dist-info/WHEEL
argsclass-0.4.1.dist-info/top_level.txt
argsclass-0.4.1.dist-info/RECORD
